streamd/__init__.py
streamd/run_gbsa.py
streamd/run_md.py
streamd/analysis/__init__.py
streamd/analysis/md_system_analysis.py
streamd/analysis/plot_build.py
streamd/analysis/run_analysis.py
streamd/analysis/xvg2png.py
streamd/example/instructions.txt
streamd/example/ligand.mol
streamd/example/protein_HIS.pdb
streamd/mcpbpy_md/__init__.py
streamd/mcpbpy_md/mcbpy_md.py
streamd/preparation/__init__.py
streamd/preparation/complex_preparation.py
streamd/preparation/ligand_preparation.py
streamd/preparation/mcpbpy_preparation.py
streamd/preparation/md_files_preparation.py
streamd/preparation/nonstandard_solvent_preparation.py
streamd/prolif/__init__.py
streamd/prolif/prolif2png.py
streamd/prolif/prolif_frame_map.py
streamd/prolif/run_prolif.py
streamd/scripts/__init__.py
streamd/scripts/getcharge.py
streamd/scripts/mol2_fix_coordsbonds.py
streamd/scripts/pdb2mol.py
streamd/scripts/pmed_amb2gmx.py
streamd/scripts/prepare_Gaussian_input.py
streamd/scripts/tleap.in
streamd/scripts/com/1.com
streamd/scripts/com/2.com
streamd/scripts/com/3.com
streamd/scripts/gbsa/mmpbsa.in
streamd/scripts/mcpbpy_scripts/protein.in
streamd/scripts/mdp/ions.mdp
streamd/scripts/mdp/md.mdp
streamd/scripts/mdp/minim.mdp
streamd/scripts/mdp/npt.mdp
streamd/scripts/mdp/nvt.mdp
streamd/scripts/script_sh/continue_md.sh
streamd/scripts/script_sh/equlibration.sh
streamd/scripts/script_sh/ligand_mol2prep.sh
streamd/scripts/script_sh/ligand_mol2prep_by_gaussian.sh
streamd/scripts/script_sh/ligand_prep.sh
streamd/scripts/script_sh/md.sh
streamd/scripts/script_sh/md_analysis.sh
streamd/scripts/script_sh/md_ligand_analysis.sh
streamd/scripts/script_sh/solv_ions.sh
streamd/tests/__init__.py
streamd/tests/analysis_test.py
streamd/tests/config_cli_test.py
streamd/tests/conftest.py
streamd/tests/decomp_dat_parser_test.py
streamd/tests/gbsa_test.py
streamd/tests/import_test.py
streamd/tests/md_test.py
streamd/tests/plot_build_test.py
streamd/tests/preparation_test.py
streamd/tests/prolif_test.py
streamd-0.4.1.dist-info/LICENSE.txt
streamd-0.4.1.dist-info/METADATA
streamd-0.4.1.dist-info/WHEEL
streamd-0.4.1.dist-info/entry_points.txt
streamd-0.4.1.dist-info/top_level.txt
streamd-0.4.1.dist-info/RECORD
