Metadata-Version: 2.1
Name: streamd
Version: 0.4.1
Summary: Streamd Python module to facilitate molecular dynamics
Home-page: https://github.com/ci-lab-cz/streamd
Author: Aleksandra Ivanova, Olena Mokshyna, Pavel Polishchuk
Classifier: Programming Language :: Python :: 3
Classifier: Operating System :: POSIX :: Linux 
Classifier: Topic :: Scientific/Engineering :: Bio-Informatics
Classifier: Topic :: Scientific/Engineering :: Chemistry
Requires-Python: >=3.6
License-File: LICENSE.txt
Provides-Extra: rdkit
Requires-Dist: rdkit >=2017.09 ; extra == 'rdkit'
